{
    "schema_version":  "aureon-ifs-portal-evidence-capture-v1",
    "generated_at":  "2026-07-09T15:45:32+01:00",
    "operator":  "Aureon",
    "scope":  "IFS_ONLY",
    "evidence_dir":  "C:/Users/user/aureon-trading/data/research/grants/applications/ifs_portal_evidence_20260709_1545",
    "captures":  [
                     {
                         "application_number":  "10209601",
                         "slug":  "next_wave",
                         "expected_title":  "Aureon Evidence Studio for Createch AI Workflows",
                         "kind":  "track",
                         "requested_url":  "https://apply-for-innovation-funding.service.gov.uk/application/10209601/track",
                         "captured_url":  "https://apply-for-innovation-funding.service.gov.uk/application/10209601/track",
                         "browser_title":  "Application Status - Aureon Evidence Studio for Createch AI Workflows - Innovation Funding Service",
                         "h1":  "Aureon Evidence Studio for Createch AI Workflows\nApplication status",
                         "text_file":  "C:/Users/user/aureon-trading/data/research/grants/applications/ifs_portal_evidence_20260709_1545/10209601_next_wave_track.txt",
                         "html_file":  "C:/Users/user/aureon-trading/data/research/grants/applications/ifs_portal_evidence_20260709_1545/10209601_next_wave_track.html",
                         "screenshot":  "C:/Users/user/aureon-trading/data/research/grants/applications/ifs_portal_evidence_20260709_1545/10209601_next_wave_track.png",
                         "text_chars":  2629,
                         "contains_application_submitted":  true,
                         "contains_awaiting_assessment":  false,
                         "contains_application_number":  true
                     },
                     {
                         "application_number":  "10209601",
                         "slug":  "next_wave",
                         "expected_title":  "Aureon Evidence Studio for Createch AI Workflows",
                         "kind":  "print",
                         "requested_url":  "https://apply-for-innovation-funding.service.gov.uk/application/10209601/print",
                         "captured_url":  "https://apply-for-innovation-funding.service.gov.uk/application/10209601/print",
                         "browser_title":  "Print application - Innovation Funding Service",
                         "h1":  "",
                         "text_file":  "C:/Users/user/aureon-trading/data/research/grants/applications/ifs_portal_evidence_20260709_1545/10209601_next_wave_print.txt",
                         "html_file":  "C:/Users/user/aureon-trading/data/research/grants/applications/ifs_portal_evidence_20260709_1545/10209601_next_wave_print.html",
                         "screenshot":  "C:/Users/user/aureon-trading/data/research/grants/applications/ifs_portal_evidence_20260709_1545/10209601_next_wave_print.png",
                         "text_chars":  25818,
                         "contains_application_submitted":  false,
                         "contains_awaiting_assessment":  false,
                         "contains_application_number":  false
                     },
                     {
                         "application_number":  "10209992",
                         "slug":  "future_leaders_r11",
                         "expected_title":  "Aureon Evidence OS for AI-Driven Scientific Discovery and Auditable SME Automation",
                         "kind":  "track",
                         "requested_url":  "https://apply-for-innovation-funding.service.gov.uk/application/10209992/track",
                         "captured_url":  "https://apply-for-innovation-funding.service.gov.uk/application/10209992/track",
                         "browser_title":  "Application Status - Aureon Evidence OS for AI-Driven Scientific Discovery and Auditable SME Automation - Innovation Funding Service",
                         "h1":  "Aureon Evidence OS for AI-Driven Scientific Discovery and Auditable SME Automation\nApplication status",
                         "text_file":  "C:/Users/user/aureon-trading/data/research/grants/applications/ifs_portal_evidence_20260709_1545/10209992_future_leaders_r11_track.txt",
                         "html_file":  "C:/Users/user/aureon-trading/data/research/grants/applications/ifs_portal_evidence_20260709_1545/10209992_future_leaders_r11_track.html",
                         "screenshot":  "C:/Users/user/aureon-trading/data/research/grants/applications/ifs_portal_evidence_20260709_1545/10209992_future_leaders_r11_track.png",
                         "text_chars":  2699,
                         "contains_application_submitted":  true,
                         "contains_awaiting_assessment":  false,
                         "contains_application_number":  true
                     },
                     {
                         "application_number":  "10209992",
                         "slug":  "future_leaders_r11",
                         "expected_title":  "Aureon Evidence OS for AI-Driven Scientific Discovery and Auditable SME Automation",
                         "kind":  "print",
                         "requested_url":  "https://apply-for-innovation-funding.service.gov.uk/application/10209992/print",
                         "captured_url":  "https://apply-for-innovation-funding.service.gov.uk/application/10209992/print",
                         "browser_title":  "Print application - Innovation Funding Service",
                         "h1":  "Uploaded IFS_FUTURE_LEADERS_R11_10209992_ETHICS_RESPONSE_20260709.pdf",
                         "text_file":  "C:/Users/user/aureon-trading/data/research/grants/applications/ifs_portal_evidence_20260709_1545/10209992_future_leaders_r11_print.txt",
                         "html_file":  "C:/Users/user/aureon-trading/data/research/grants/applications/ifs_portal_evidence_20260709_1545/10209992_future_leaders_r11_print.html",
                         "screenshot":  "C:/Users/user/aureon-trading/data/research/grants/applications/ifs_portal_evidence_20260709_1545/10209992_future_leaders_r11_print.png",
                         "text_chars":  26186,
                         "contains_application_submitted":  false,
                         "contains_awaiting_assessment":  false,
                         "contains_application_number":  true
                     },
                     {
                         "application_number":  "10210032",
                         "slug":  "consumer_led_flexibility",
                         "expected_title":  "Aureon Flex Evidence OS: AI Assurance for Consumer-Led Flexibility",
                         "kind":  "track",
                         "requested_url":  "https://apply-for-innovation-funding.service.gov.uk/application/10210032/track",
                         "captured_url":  "https://apply-for-innovation-funding.service.gov.uk/application/10210032/track",
                         "browser_title":  "Application Status - Aureon Flex Evidence OS: AI Assurance for Consumer-Led Flexibility - Innovation Funding Service",
                         "h1":  "Aureon Flex Evidence OS: AI Assurance for Consumer-Led Flexibility\nApplication status",
                         "text_file":  "C:/Users/user/aureon-trading/data/research/grants/applications/ifs_portal_evidence_20260709_1545/10210032_consumer_led_flexibility_track.txt",
                         "html_file":  "C:/Users/user/aureon-trading/data/research/grants/applications/ifs_portal_evidence_20260709_1545/10210032_consumer_led_flexibility_track.html",
                         "screenshot":  "C:/Users/user/aureon-trading/data/research/grants/applications/ifs_portal_evidence_20260709_1545/10210032_consumer_led_flexibility_track.png",
                         "text_chars":  2683,
                         "contains_application_submitted":  true,
                         "contains_awaiting_assessment":  false,
                         "contains_application_number":  true
                     },
                     {
                         "application_number":  "10210032",
                         "slug":  "consumer_led_flexibility",
                         "expected_title":  "Aureon Flex Evidence OS: AI Assurance for Consumer-Led Flexibility",
                         "kind":  "print",
                         "requested_url":  "https://apply-for-innovation-funding.service.gov.uk/application/10210032/print",
                         "captured_url":  "https://apply-for-innovation-funding.service.gov.uk/application/10210032/print",
                         "browser_title":  "Print application - Innovation Funding Service",
                         "h1":  "",
                         "text_file":  "C:/Users/user/aureon-trading/data/research/grants/applications/ifs_portal_evidence_20260709_1545/10210032_consumer_led_flexibility_print.txt",
                         "html_file":  "C:/Users/user/aureon-trading/data/research/grants/applications/ifs_portal_evidence_20260709_1545/10210032_consumer_led_flexibility_print.html",
                         "screenshot":  "C:/Users/user/aureon-trading/data/research/grants/applications/ifs_portal_evidence_20260709_1545/10210032_consumer_led_flexibility_print.png",
                         "text_chars":  21820,
                         "contains_application_submitted":  false,
                         "contains_awaiting_assessment":  false,
                         "contains_application_number":  true
                     },
                     {
                         "application_number":  "10210045",
                         "slug":  "cfi_sen",
                         "expected_title":  "Aureon SEN Evidence OS: Fair Early Identification Support",
                         "kind":  "track",
                         "requested_url":  "https://apply-for-innovation-funding.service.gov.uk/application/10210045/track",
                         "captured_url":  "https://apply-for-innovation-funding.service.gov.uk/application/10210045/track",
                         "browser_title":  "Application Status - Aureon SEN Evidence OS: Fair Early Identification Support - Innovation Funding Service",
                         "h1":  "Aureon SEN Evidence OS: Fair Early Identification Support\nApplication status",
                         "text_file":  "C:/Users/user/aureon-trading/data/research/grants/applications/ifs_portal_evidence_20260709_1545/10210045_cfi_sen_track.txt",
                         "html_file":  "C:/Users/user/aureon-trading/data/research/grants/applications/ifs_portal_evidence_20260709_1545/10210045_cfi_sen_track.html",
                         "screenshot":  "C:/Users/user/aureon-trading/data/research/grants/applications/ifs_portal_evidence_20260709_1545/10210045_cfi_sen_track.png",
                         "text_chars":  1655,
                         "contains_application_submitted":  true,
                         "contains_awaiting_assessment":  false,
                         "contains_application_number":  true
                     },
                     {
                         "application_number":  "10210045",
                         "slug":  "cfi_sen",
                         "expected_title":  "Aureon SEN Evidence OS: Fair Early Identification Support",
                         "kind":  "print",
                         "requested_url":  "https://apply-for-innovation-funding.service.gov.uk/application/10210045/print",
                         "captured_url":  "https://apply-for-innovation-funding.service.gov.uk/application/10210045/print",
                         "browser_title":  "Print application - Innovation Funding Service",
                         "h1":  "",
                         "text_file":  "C:/Users/user/aureon-trading/data/research/grants/applications/ifs_portal_evidence_20260709_1545/10210045_cfi_sen_print.txt",
                         "html_file":  "C:/Users/user/aureon-trading/data/research/grants/applications/ifs_portal_evidence_20260709_1545/10210045_cfi_sen_print.html",
                         "screenshot":  "C:/Users/user/aureon-trading/data/research/grants/applications/ifs_portal_evidence_20260709_1545/10210045_cfi_sen_print.png",
                         "text_chars":  19148,
                         "contains_application_submitted":  false,
                         "contains_awaiting_assessment":  false,
                         "contains_application_number":  false
                     }
                 ]
}
