{
  "timestamp": 1767567001.4324043,
  "timestamp_readable": "2026-01-04 22:50:01 UTC",
  "uk_mode": true,
  "trade_groups": [
    "TRD_GRP_039"
  ],
  "allowed_pairs": [
    "0GBNB",
    "0GUSDC",
    "1000CATUSDC",
    "1000CHEEMSUSDC",
    "1000SATSUSDC",
    "1INCHBTC",
    "1INCHUSDC",
    "1MBABYDOGEUSDC",
    "2ZBNB",
    "2ZUSDC",
    "A2ZUSDC",
    "AAVEBTC",
    "AAVEETH",
    "AAVEUSDC",
    "ABTC",
    "ACHUSDC",
    "ACTUSDC",
    "ACXUSDC",
    "ADABNB",
    "ADABRL",
    "ADABTC",
    "ADAETH",
    "ADAEUR",
    "ADAJPY",
    "ADAUSDC",
    "ADXBTC",
    "ADXETH",
    "AEVOBTC",
    "AEVOUSDC",
    "AGLDBTC",
    "AIBTC",
    "AIXBTUSDC",
    "ALGOBTC",
    "ALGOUSDC",
    "ALLOBNB",
    "ALLOUSDC",
    "ALTBNB",
    "ALTBTC",
    "ALTUSDC",
    "ANIMEUSDC",
    "APEBTC",
    "APEUSDC",
    "API3BTC",
    "API3USDC",
    "APTBTC",
    "APTETH",
    "APTEUR",
    "APTJPY",
    "APTUSDC",
    "ARBBTC",
    "ARBETH",
    "ARBEUR",
    "ARBTC",
    "ARDRBTC",
    "ARKMBTC",
    "ARKMUSDC",
    "ARPABTC",
    "ARUSDC",
    "ASTERUSDC",
    "ASTRBTC",
    "ATBNB",
    "ATOMBTC",
    "ATOMETH",
    "ATOMEUR",
    "ATOMUSDC",
    "ATUSDC",
    "AUCTIONBTC",
    "AUCTIONUSDC",
    "AUDIOBTC",
    "AUSDC",
    "AVABTC",
    "AVAXBNB",
    "AVAXBRL",
    "AVAXBTC",
    "AVAXETH",
    "AVAXEUR",
    "AVAXUSDC",
    "AVNTUSDC",
    "AWEBTC",
    "AXLBTC",
    "AXSBTC",
    "AXSETH",
    "AXSUSDC",
    "BABYUSDC",
    "BANANABNB",
    "BANANABTC",
    "BANANAS31USDC",
    "BANANAUSDC",
    "BANDBTC",
    "BANKUSDC",
    "BARDUSDC",
    "BATBTC",
    "BBBNB",
    "BBBTC",
    "BCHBNB",
    "BCHBTC",
    "BCHEUR",
    "BCHJPY",
    "BCHUSDC",
    "BEAMXUSDC",
    "BELBTC",
    "BERABNB",
    "BERABTC",
    "BERAUSDC",
    "BIGTIMEUSDC",
    "BIOBNB",
    "BIOUSDC",
    "BLURUSDC",
    "BMTUSDC",
    "BNBARS",
    "BNBBRL",
    "BNBBTC",
    "BNBETH",
    "BNBEUR",
    "BNBJPY",
    "BNSOLSOL",
    "BOMEUSDC",
    "BONKBRL",
    "BONKUSDC",
    "BROCCOLI714USDC",
    "BTCARS",
    "BTCBRL",
    "BTCEUR",
    "BTCEURI",
    "BTCJPY",
    "BTCMXN",
    "BTCPLN",
    "BTCUAH",
    "BTCUSD",
    "BTCUSDC",
    "BTCZAR",
    "CAKEBNB",
    "CAKEBTC",
    "CAKEUSDC",
    "CATIUSDC",
    "CELOBTC",
    "CETUSUSDC",
    "CFXBTC",
    "CFXUSDC",
    "CGPTUSDC",
    "CHESSUSDC",
    "CHZBNB",
    "CHZBTC",
    "CHZUSDC",
    "COMPBTC",
    "COMPUSDC",
    "COOKIEUSDC",
    "COTIBTC",
    "COTIUSDC",
    "COWUSDC",
    "CRVBTC",
    "CRVUSDC",
    "CTKBNB",
    "CTKBTC",
    "CTSIBTC",
    "CUSDC",
    "CVCUSDC",
    "CVXUSDC",
    "CYBERBNB",
    "CYBERBTC",
    "CYBERETH",
    "CYBERUSDC",
    "DASHBTC",
    "DASHETH",
    "DASHUSDC",
    "DFUSDC",
    "DIABTC",
    "DODOBTC",
    "DOGEBRL",
    "DOGEBTC",
    "DOGEEUR",
    "DOGEJPY",
    "DOGEUSDC",
    "DOGSUSDC",
    "DOLOUSDC",
    "DOTBNB",
    "DOTBRL",
    "DOTBTC",
    "DOTETH",
    "DOTEUR",
    "DOTUSDC",
    "DUSKBTC",
    "DYDXBTC",
    "DYDXUSDC",
    "DYMUSDC",
    "EDENBNB",
    "EDENUSDC",
    "EGLDBNB",
    "EGLDBTC",
    "EGLDETH",
    "EGLDEUR",
    "EGLDUSDC",
    "EIGENBTC",
    "EIGENUSDC",
    "ENABNB",
    "ENABRL",
    "ENABTC",
    "ENAUSDC",
    "ENJUSDC",
    "ENSBTC",
    "ENSOBNB",
    "ENSOUSDC",
    "ENSUSDC",
    "EPICUSDC",
    "ERABNB",
    "ERAUSDC",
    "ETCBTC",
    "ETCETH",
    "ETCUSDC",
    "ETHARS",
    "ETHBRL",
    "ETHBTC",
    "ETHEUR",
    "ETHEURI",
    "ETHFIUSDC",
    "ETHJPY",
    "ETHMXN",
    "ETHPLN",
    "ETHUSDC",
    "ETHZAR",
    "EULBNB",
    "EULUSDC",
    "EUREURI",
    "EURIUSDC",
    "EURUSDC",
    "FETBNB",
    "FETBTC",
    "FETUSDC",
    "FFBNB",
    "FFUSDC",
    "FIDABTC",
    "FILBTC",
    "FILETH",
    "FILUSDC",
    "FLOKIUSDC",
    "FLUXBTC",
    "FLUXUSDC",
    "FORMUSDC",
    "FORTHBTC",
    "FUNUSDC",
    "FUSDC",
    "GALABRL",
    "GALAETH",
    "GALAEUR",
    "GALAUSDC",
    "GASBTC",
    "GIGGLEUSDC",
    "GLMBTC",
    "GLMRBTC",
    "GMTEUR",
    "GMTUSDC",
    "GMXUSDC",
    "GPSBNB",
    "GPSUSDC",
    "GRTBTC",
    "GRTETH",
    "GRTEUR",
    "GRTUSDC",
    "GUNBNB",
    "GUNUSDC",
    "HAEDALUSDC",
    "HBARBNB",
    "HBARBTC",
    "HBARUSDC",
    "HEIBTC",
    "HEIUSDC",
    "HEMIBNB",
    "HEMIUSDC",
    "HFTBTC",
    "HIVEBTC",
    "HIVEUSDC",
    "HOLOBNB",
    "HOLOUSDC",
    "HOMEUSDC",
    "HOTETH",
    "HUMAUSDC",
    "HYPERUSDC",
    "ICPBTC",
    "ICPETH",
    "ICPEUR",
    "ICPUSDC",
    "ICXBTC",
    "IDBTC",
    "IDEXUSDC",
    "ILVBTC",
    "ILVUSDC",
    "IMXBTC",
    "IMXUSDC",
    "INITUSDC",
    "INJBNB",
    "INJBTC",
    "INJUSDC",
    "IOBNB",
    "IOBTC",
    "IOTABTC",
    "IOTAETH",
    "IOTAUSDC",
    "IOTXETH",
    "IOTXJPY",
    "IOUSDC",
    "JOEBTC",
    "JSTBTC",
    "JTOUSDC",
    "JUPUSDC",
    "JUVUSDC",
    "KAIAUSDC",
    "KAITOBTC",
    "KAITOUSDC",
    "KAVABTC",
    "KERNELBNB",
    "KERNELUSDC",
    "KITEBNB",
    "KITEUSDC",
    "KMNOUSDC",
    "KNCBTC",
    "KSMBTC",
    "LABNB",
    "LAUSDC",
    "LAYERBTC",
    "LAYERUSDC",
    "LDOBTC",
    "LDOUSDC",
    "LINEABNB",
    "LINEAUSDC",
    "LINKBNB",
    "LINKBRL",
    "LINKBTC",
    "LINKETH",
    "LINKEUR",
    "LINKJPY",
    "LINKUSDC",
    "LISTAUSDC",
    "LPTBTC",
    "LPTJPY",
    "LPTUSDC",
    "LRCBTC",
    "LRCETH",
    "LSKBTC",
    "LSKUSDC",
    "LTCBNB",
    "LTCBRL",
    "LTCBTC",
    "LTCETH",
    "LTCEUR",
    "LTCJPY",
    "LTCUSDC",
    "LUNAUSDC",
    "LUNCUSDC",
    "MAGICBTC",
    "MAGICUSDC",
    "MANABTC",
    "MANAETH",
    "MANTABTC",
    "MANTAUSDC",
    "MASKUSDC",
    "MAVBTC",
    "MAVUSDC",
    "MEMEUSDC",
    "METUSDC",
    "MEUSDC",
    "MINABTC",
    "MINAUSDC",
    "MIRABNB",
    "MIRAUSDC",
    "MITOUSDC",
    "MMTBNB",
    "MMTUSDC",
    "MORPHOBNB",
    "MORPHOUSDC",
    "MOVEBNB",
    "MOVEUSDC",
    "MOVRBTC",
    "MTLBTC",
    "MUBARAKUSDC",
    "NEARBNB",
    "NEARBRL",
    "NEARBTC",
    "NEARETH",
    "NEAREUR",
    "NEARJPY",
    "NEARUSDC",
    "NEIROJPY",
    "NEIROUSDC",
    "NEOBTC",
    "NEOUSDC",
    "NEWTUSDC",
    "NEXOBTC",
    "NFPBTC",
    "NILUSDC",
    "NMRBTC",
    "NMRUSDC",
    "NOMUSDC",
    "NOTUSDC",
    "NTRNBNB",
    "NXPCUSDC",
    "OGBTC",
    "OGNBTC",
    "OMUSDC",
    "ONDOUSDC",
    "ONGBTC",
    "ONTBTC",
    "ONTUSDC",
    "OPBTC",
    "OPENBNB",
    "OPENUSDC",
    "OPETH",
    "OPEUR",
    "OPUSDC",
    "ORCAUSDC",
    "ORDIBTC",
    "ORDIUSDC",
    "OSMOUSDC",
    "OXTBTC",
    "PARTIBNB",
    "PARTIUSDC",
    "PENDLEBTC",
    "PENDLEUSDC",
    "PENGUUSDC",
    "PEOPLEUSDC",
    "PEPEBRL",
    "PEPEEUR",
    "PEPEJPY",
    "PEPEUSDC",
    "PHABTC",
    "PHAUSDC",
    "PHBBTC",
    "PIVXBTC",
    "PIXELUSDC",
    "PLUMEBNB",
    "PLUMEUSDC",
    "PNUTBTC",
    "PNUTEUR",
    "PNUTUSDC",
    "POLBNB",
    "POLBRL",
    "POLBTC",
    "POLETH",
    "POLEUR",
    "POLJPY",
    "POLUSDC",
    "POLYXBTC",
    "PROVEUSDC",
    "PUMPUSDC",
    "PUNDIXUSDC",
    "PYRBTC",
    "PYTHBTC",
    "PYTHUSDC",
    "QNTBTC",
    "QNTUSDC",
    "QTUMETH",
    "QTUMUSDC",
    "RAREBTC",
    "RAREUSDC",
    "RAYUSDC",
    "REDBTC",
    "REDUSDC",
    "RENDERBRL",
    "RENDERBTC",
    "RENDEREUR",
    "RENDERUSDC",
    "REQBTC",
    "RESOLVUSDC",
    "REZUSDC",
    "RLCBTC",
    "RLCETH",
    "RONINBTC",
    "ROSEBTC",
    "ROSEUSDC",
    "RPLUSDC",
    "RSRUSDC",
    "RUNEBTC",
    "RUNEETH",
    "RUNEUSDC",
    "RVNUSDC",
    "SAGABNB",
    "SAGABTC",
    "SAGAUSDC",
    "SAHARAUSDC",
    "SANDBTC",
    "SANDUSDC",
    "SANTOSBTC",
    "SAPIENBNB",
    "SAPIENUSDC",
    "SBNB",
    "SBTC",
    "SCETH",
    "SCRBTC",
    "SCRTBTC",
    "SEIBNB",
    "SEIBTC",
    "SEIJPY",
    "SEIUSDC",
    "SETH",
    "SEUR",
    "SHELLBTC",
    "SHELLUSDC",
    "SHIBBRL",
    "SHIBDOGE",
    "SHIBEUR",
    "SHIBJPY",
    "SIGNBNB",
    "SIGNUSDC",
    "SKLBTC",
    "SKLUSDC",
    "SKYBTC",
    "SKYUSDC",
    "SLPETH",
    "SNXBTC",
    "SNXUSDC",
    "SOLARS",
    "SOLBNB",
    "SOLBRL",
    "SOLBTC",
    "SOLETH",
    "SOLEUR",
    "SOLJPY",
    "SOLMXN",
    "SOLUSDC",
    "SOLVBNB",
    "SOLVUSDC",
    "SOMIBNB",
    "SOMIUSDC",
    "SOPHUSDC",
    "SPKUSDC",
    "SSVBTC",
    "SSVETH",
    "SSVUSDC",
    "STEEMBTC",
    "STEEMETH",
    "STEEMUSDC",
    "STGBTC",
    "STORJBTC",
    "STOUSDC",
    "STRKUSDC",
    "STXBTC",
    "STXUSDC",
    "SUIBNB",
    "SUIBRL",
    "SUIBTC",
    "SUIEUR",
    "SUIJPY",
    "SUIUSDC",
    "SUPERBTC",
    "SUSDC",
    "SUSHIBTC",
    "SUSHIUSDC",
    "SXPBTC",
    "SXTUSDC",
    "SYNUSDC",
    "SYRUPUSDC",
    "SYSBTC",
    "TAOBTC",
    "TAOUSDC",
    "TFUELBTC",
    "THETABTC",
    "THETAUSDC",
    "THEUSDC",
    "TIABTC",
    "TIAUSDC",
    "TLMUSDC",
    "TNSRUSDC",
    "TONBTC",
    "TONUSDC",
    "TOWNSUSDC",
    "TRBBTC",
    "TREEUSDC",
    "TRUMPBRL",
    "TRUMPEUR",
    "TRUMPJPY",
    "TRUMPUSDC",
    "TRXBNB",
    "TRXBTC",
    "TRXETH",
    "TRXEUR",
    "TRXJPY",
    "TRXUSDC",
    "TRXXRP",
    "TSTUSDC",
    "TURBOUSDC",
    "TURTLEBNB",
    "TURTLEUSDC",
    "TUSDC",
    "TUTUSDC",
    "TWTUSDC",
    "UMAUSDC",
    "UNIBTC",
    "UNIETH",
    "UNIUSDC",
    "USDCBRL",
    "USDCCZK",
    "USDCPLN",
    "USDCRON",
    "USDCUSD",
    "USUALUSDC",
    "UTKUSDC",
    "VANAUSDC",
    "VANRYUSDC",
    "VELODROMEUSDC",
    "VETBTC",
    "VETETH",
    "VETEUR",
    "VETUSDC",
    "VIRTUALUSDC",
    "WALBNB",
    "WALUSDC",
    "WANBTC",
    "WBETHETH",
    "WBTCBTC",
    "WBTCETH",
    "WCTBNB",
    "WCTUSDC",
    "WIFBTC",
    "WIFEUR",
    "WIFUSDC",
    "WINEUR",
    "WINTRX",
    "WLDBTC",
    "WLDEUR",
    "WLDUSDC",
    "WLFIEUR",
    "WLFIUSDC",
    "WUSDC",
    "XAIUSDC",
    "XLMBTC",
    "XLMETH",
    "XLMEUR",
    "XLMJPY",
    "XLMUSDC",
    "XNOBTC",
    "XPLBNB",
    "XPLUSDC",
    "XRPBNB",
    "XRPBRL",
    "XRPBTC",
    "XRPETH",
    "XRPEUR",
    "XRPJPY",
    "XRPMXN",
    "XRPUSDC",
    "XTZBTC",
    "XTZUSDC",
    "XVGETH",
    "XVGUSDC",
    "XVSBNB",
    "XVSBTC",
    "YBBNB",
    "YFIBTC",
    "YGGBTC",
    "YGGUSDC",
    "ZBTBNB",
    "ZBTUSDC",
    "ZECBTC",
    "ZECETH",
    "ZECUSDC",
    "ZENBTC",
    "ZENUSDC",
    "ZILETH",
    "ZKBTC",
    "ZKCUSDC",
    "ZKUSDC",
    "ZROBTC",
    "ZROUSDC"
  ],
  "allowed_base_assets": [
    "0G",
    "1000CAT",
    "1000CHEEMS",
    "1000SATS",
    "1INCH",
    "1MBABYDOGE",
    "2Z",
    "A",
    "A2Z",
    "AAVE",
    "ACH",
    "ACT",
    "ACX",
    "ADA",
    "ADX",
    "AEVO",
    "AGLD",
    "AI",
    "AIXBT",
    "ALGO",
    "ALLO",
    "ALT",
    "ANIME",
    "APE",
    "API3",
    "APT",
    "AR",
    "ARB",
    "ARDR",
    "ARKM",
    "ARPA",
    "ASTER",
    "ASTR",
    "AT",
    "ATOM",
    "AUCTION",
    "AUDIO",
    "AVA",
    "AVAX",
    "AVNT",
    "AWE",
    "AXL",
    "AXS",
    "BABY",
    "BANANA",
    "BANANAS31",
    "BAND",
    "BANK",
    "BARD",
    "BAT",
    "BB",
    "BCH",
    "BEAMX",
    "BEL",
    "BERA",
    "BIGTIME",
    "BIO",
    "BLUR",
    "BMT",
    "BNB",
    "BNSOL",
    "BOME",
    "BONK",
    "BROCCOLI714",
    "BTC",
    "C",
    "CAKE",
    "CATI",
    "CELO",
    "CETUS",
    "CFX",
    "CGPT",
    "CHESS",
    "CHZ",
    "COMP",
    "COOKIE",
    "COTI",
    "COW",
    "CRV",
    "CTK",
    "CTSI",
    "CVC",
    "CVX",
    "CYBER",
    "DASH",
    "DF",
    "DIA",
    "DODO",
    "DOGE",
    "DOGS",
    "DOLO",
    "DOT",
    "DUSK",
    "DYDX",
    "DYM",
    "EDEN",
    "EGLD",
    "EIGEN",
    "ENA",
    "ENJ",
    "ENS",
    "ENSO",
    "EPIC",
    "ERA",
    "ETC",
    "ETH",
    "ETHFI",
    "EUL",
    "EUR",
    "EURI",
    "F",
    "FET",
    "FF",
    "FIDA",
    "FIL",
    "FLOKI",
    "FLUX",
    "FORM",
    "FORTH",
    "FUN",
    "GALA",
    "GAS",
    "GIGGLE",
    "GLM",
    "GLMR",
    "GMT",
    "GMX",
    "GPS",
    "GRT",
    "GUN",
    "HAEDAL",
    "HBAR",
    "HEI",
    "HEMI",
    "HFT",
    "HIVE",
    "HOLO",
    "HOME",
    "HOT",
    "HUMA",
    "HYPER",
    "ICP",
    "ICX",
    "ID",
    "IDEX",
    "ILV",
    "IMX",
    "INIT",
    "INJ",
    "IO",
    "IOTA",
    "IOTX",
    "JOE",
    "JST",
    "JTO",
    "JUP",
    "JUV",
    "KAIA",
    "KAITO",
    "KAVA",
    "KERNEL",
    "KITE",
    "KMNO",
    "KNC",
    "KSM",
    "LA",
    "LAYER",
    "LDO",
    "LINEA",
    "LINK",
    "LISTA",
    "LPT",
    "LRC",
    "LSK",
    "LTC",
    "LUNA",
    "LUNC",
    "MAGIC",
    "MANA",
    "MANTA",
    "MASK",
    "MAV",
    "ME",
    "MEME",
    "MET",
    "MINA",
    "MIRA",
    "MITO",
    "MMT",
    "MORPHO",
    "MOVE",
    "MOVR",
    "MTL",
    "MUBARAK",
    "NEAR",
    "NEIRO",
    "NEO",
    "NEWT",
    "NEXO",
    "NFP",
    "NIL",
    "NMR",
    "NOM",
    "NOT",
    "NTRN",
    "NXPC",
    "OG",
    "OGN",
    "OM",
    "ONDO",
    "ONG",
    "ONT",
    "OP",
    "OPEN",
    "ORCA",
    "ORDI",
    "OSMO",
    "OXT",
    "PARTI",
    "PENDLE",
    "PENGU",
    "PEOPLE",
    "PEPE",
    "PHA",
    "PHB",
    "PIVX",
    "PIXEL",
    "PLUME",
    "PNUT",
    "POL",
    "POLYX",
    "PROVE",
    "PUMP",
    "PUNDIX",
    "PYR",
    "PYTH",
    "QNT",
    "QTUM",
    "RARE",
    "RAY",
    "RED",
    "RENDER",
    "REQ",
    "RESOLV",
    "REZ",
    "RLC",
    "RONIN",
    "ROSE",
    "RPL",
    "RSR",
    "RUNE",
    "RVN",
    "S",
    "SAGA",
    "SAHARA",
    "SAND",
    "SANTOS",
    "SAPIEN",
    "SC",
    "SCR",
    "SCRT",
    "SEI",
    "SHELL",
    "SHIB",
    "SIGN",
    "SKL",
    "SKY",
    "SLP",
    "SNX",
    "SOL",
    "SOLV",
    "SOMI",
    "SOPH",
    "SPK",
    "SSV",
    "STEEM",
    "STG",
    "STO",
    "STORJ",
    "STRK",
    "STX",
    "SUI",
    "SUPER",
    "SUSHI",
    "SXP",
    "SXT",
    "SYN",
    "SYRUP",
    "SYS",
    "T",
    "TAO",
    "TFUEL",
    "THE",
    "THETA",
    "TIA",
    "TLM",
    "TNSR",
    "TON",
    "TOWNS",
    "TRB",
    "TREE",
    "TRUMP",
    "TRX",
    "TST",
    "TURBO",
    "TURTLE",
    "TUT",
    "TWT",
    "UMA",
    "UNI",
    "USDC",
    "USUAL",
    "UTK",
    "VANA",
    "VANRY",
    "VELODROME",
    "VET",
    "VIRTUAL",
    "W",
    "WAL",
    "WAN",
    "WBETH",
    "WBTC",
    "WCT",
    "WIF",
    "WIN",
    "WLD",
    "WLFI",
    "XAI",
    "XLM",
    "XNO",
    "XPL",
    "XRP",
    "XTZ",
    "XVG",
    "XVS",
    "YB",
    "YFI",
    "YGG",
    "ZBT",
    "ZEC",
    "ZEN",
    "ZIL",
    "ZK",
    "ZKC",
    "ZRO"
  ],
  "allowed_quote_assets": [
    "ARS",
    "BNB",
    "BRL",
    "BTC",
    "CZK",
    "DOGE",
    "ETH",
    "EUR",
    "EURI",
    "JPY",
    "MXN",
    "PLN",
    "RON",
    "SOL",
    "TRX",
    "UAH",
    "USD",
    "USDC",
    "XRP",
    "ZAR"
  ],
  "pairs_by_quote": {
    "BTC": [
      "1INCHBTC",
      "AAVEBTC",
      "ABTC",
      "ADABTC",
      "ADXBTC",
      "AEVOBTC",
      "AGLDBTC",
      "AIBTC",
      "ALGOBTC",
      "ALTBTC",
      "APEBTC",
      "API3BTC",
      "APTBTC",
      "ARBBTC",
      "ARBTC",
      "ARDRBTC",
      "ARKMBTC",
      "ARPABTC",
      "ASTRBTC",
      "ATOMBTC",
      "AUCTIONBTC",
      "AUDIOBTC",
      "AVABTC",
      "AVAXBTC",
      "AWEBTC",
      "AXLBTC",
      "AXSBTC",
      "BANANABTC",
      "BANDBTC",
      "BATBTC",
      "BBBTC",
      "BCHBTC",
      "BELBTC",
      "BERABTC",
      "BNBBTC",
      "CAKEBTC",
      "CELOBTC",
      "CFXBTC",
      "CHZBTC",
      "COMPBTC",
      "COTIBTC",
      "CRVBTC",
      "CTKBTC",
      "CTSIBTC",
      "CYBERBTC",
      "DASHBTC",
      "DIABTC",
      "DODOBTC",
      "DOGEBTC",
      "DOTBTC",
      "DUSKBTC",
      "DYDXBTC",
      "EGLDBTC",
      "EIGENBTC",
      "ENABTC",
      "ENSBTC",
      "ETCBTC",
      "ETHBTC",
      "FETBTC",
      "FIDABTC",
      "FILBTC",
      "FLUXBTC",
      "FORTHBTC",
      "GASBTC",
      "GLMBTC",
      "GLMRBTC",
      "GRTBTC",
      "HBARBTC",
      "HEIBTC",
      "HFTBTC",
      "HIVEBTC",
      "ICPBTC",
      "ICXBTC",
      "IDBTC",
      "ILVBTC",
      "IMXBTC",
      "INJBTC",
      "IOBTC",
      "IOTABTC",
      "JOEBTC",
      "JSTBTC",
      "KAITOBTC",
      "KAVABTC",
      "KNCBTC",
      "KSMBTC",
      "LAYERBTC",
      "LDOBTC",
      "LINKBTC",
      "LPTBTC",
      "LRCBTC",
      "LSKBTC",
      "LTCBTC",
      "MAGICBTC",
      "MANABTC",
      "MANTABTC",
      "MAVBTC",
      "MINABTC",
      "MOVRBTC",
      "MTLBTC",
      "NEARBTC",
      "NEOBTC",
      "NEXOBTC",
      "NFPBTC",
      "NMRBTC",
      "OGBTC",
      "OGNBTC",
      "ONGBTC",
      "ONTBTC",
      "OPBTC",
      "ORDIBTC",
      "OXTBTC",
      "PENDLEBTC",
      "PHABTC",
      "PHBBTC",
      "PIVXBTC",
      "PNUTBTC",
      "POLBTC",
      "POLYXBTC",
      "PYRBTC",
      "PYTHBTC",
      "QNTBTC",
      "RAREBTC",
      "REDBTC",
      "RENDERBTC",
      "REQBTC",
      "RLCBTC",
      "RONINBTC",
      "ROSEBTC",
      "RUNEBTC",
      "SAGABTC",
      "SANDBTC",
      "SANTOSBTC",
      "SBTC",
      "SCRBTC",
      "SCRTBTC",
      "SEIBTC",
      "SHELLBTC",
      "SKLBTC",
      "SKYBTC",
      "SNXBTC",
      "SOLBTC",
      "SSVBTC",
      "STEEMBTC",
      "STGBTC",
      "STORJBTC",
      "STXBTC",
      "SUIBTC",
      "SUPERBTC",
      "SUSHIBTC",
      "SXPBTC",
      "SYSBTC",
      "TAOBTC",
      "TFUELBTC",
      "THETABTC",
      "TIABTC",
      "TONBTC",
      "TRBBTC",
      "TRXBTC",
      "UNIBTC",
      "VETBTC",
      "WANBTC",
      "WBTCBTC",
      "WIFBTC",
      "WLDBTC",
      "XLMBTC",
      "XNOBTC",
      "XRPBTC",
      "XTZBTC",
      "XVSBTC",
      "YFIBTC",
      "YGGBTC",
      "ZECBTC",
      "ZENBTC",
      "ZKBTC",
      "ZROBTC"
    ],
    "ETH": [
      "AAVEETH",
      "ADAETH",
      "ADXETH",
      "APTETH",
      "ARBETH",
      "ATOMETH",
      "AVAXETH",
      "AXSETH",
      "BNBETH",
      "CYBERETH",
      "DASHETH",
      "DOTETH",
      "EGLDETH",
      "ETCETH",
      "FILETH",
      "GALAETH",
      "GRTETH",
      "HOTETH",
      "ICPETH",
      "IOTAETH",
      "IOTXETH",
      "LINKETH",
      "LRCETH",
      "LTCETH",
      "MANAETH",
      "NEARETH",
      "OPETH",
      "POLETH",
      "QTUMETH",
      "RLCETH",
      "RUNEETH",
      "SCETH",
      "SETH",
      "SLPETH",
      "SOLETH",
      "SSVETH",
      "STEEMETH",
      "TRXETH",
      "UNIETH",
      "VETETH",
      "WBETHETH",
      "WBTCETH",
      "XLMETH",
      "XRPETH",
      "XVGETH",
      "ZECETH",
      "ZILETH"
    ],
    "BNB": [
      "0GBNB",
      "2ZBNB",
      "ADABNB",
      "ALLOBNB",
      "ALTBNB",
      "ATBNB",
      "AVAXBNB",
      "BANANABNB",
      "BBBNB",
      "BCHBNB",
      "BERABNB",
      "BIOBNB",
      "CAKEBNB",
      "CHZBNB",
      "CTKBNB",
      "CYBERBNB",
      "DOTBNB",
      "EDENBNB",
      "EGLDBNB",
      "ENABNB",
      "ENSOBNB",
      "ERABNB",
      "EULBNB",
      "FETBNB",
      "FFBNB",
      "GPSBNB",
      "GUNBNB",
      "HBARBNB",
      "HEMIBNB",
      "HOLOBNB",
      "INJBNB",
      "IOBNB",
      "KERNELBNB",
      "KITEBNB",
      "LABNB",
      "LINEABNB",
      "LINKBNB",
      "LTCBNB",
      "MIRABNB",
      "MMTBNB",
      "MORPHOBNB",
      "MOVEBNB",
      "NEARBNB",
      "NTRNBNB",
      "OPENBNB",
      "PARTIBNB",
      "PLUMEBNB",
      "POLBNB",
      "SAGABNB",
      "SAPIENBNB",
      "SBNB",
      "SEIBNB",
      "SIGNBNB",
      "SOLBNB",
      "SOLVBNB",
      "SOMIBNB",
      "SUIBNB",
      "TRXBNB",
      "TURTLEBNB",
      "WALBNB",
      "WCTBNB",
      "XPLBNB",
      "XRPBNB",
      "XVSBNB",
      "YBBNB",
      "ZBTBNB"
    ],
    "USDC": [
      "0GUSDC",
      "1000CATUSDC",
      "1000CHEEMSUSDC",
      "1000SATSUSDC",
      "1INCHUSDC",
      "1MBABYDOGEUSDC",
      "2ZUSDC",
      "A2ZUSDC",
      "AAVEUSDC",
      "ACHUSDC",
      "ACTUSDC",
      "ACXUSDC",
      "ADAUSDC",
      "AEVOUSDC",
      "AIXBTUSDC",
      "ALGOUSDC",
      "ALLOUSDC",
      "ALTUSDC",
      "ANIMEUSDC",
      "APEUSDC",
      "API3USDC",
      "APTUSDC",
      "ARKMUSDC",
      "ARUSDC",
      "ASTERUSDC",
      "ATOMUSDC",
      "ATUSDC",
      "AUCTIONUSDC",
      "AUSDC",
      "AVAXUSDC",
      "AVNTUSDC",
      "AXSUSDC",
      "BABYUSDC",
      "BANANAS31USDC",
      "BANANAUSDC",
      "BANKUSDC",
      "BARDUSDC",
      "BCHUSDC",
      "BEAMXUSDC",
      "BERAUSDC",
      "BIGTIMEUSDC",
      "BIOUSDC",
      "BLURUSDC",
      "BMTUSDC",
      "BOMEUSDC",
      "BONKUSDC",
      "BROCCOLI714USDC",
      "BTCUSDC",
      "CAKEUSDC",
      "CATIUSDC",
      "CETUSUSDC",
      "CFXUSDC",
      "CGPTUSDC",
      "CHESSUSDC",
      "CHZUSDC",
      "COMPUSDC",
      "COOKIEUSDC",
      "COTIUSDC",
      "COWUSDC",
      "CRVUSDC",
      "CUSDC",
      "CVCUSDC",
      "CVXUSDC",
      "CYBERUSDC",
      "DASHUSDC",
      "DFUSDC",
      "DOGEUSDC",
      "DOGSUSDC",
      "DOLOUSDC",
      "DOTUSDC",
      "DYDXUSDC",
      "DYMUSDC",
      "EDENUSDC",
      "EGLDUSDC",
      "EIGENUSDC",
      "ENAUSDC",
      "ENJUSDC",
      "ENSOUSDC",
      "ENSUSDC",
      "EPICUSDC",
      "ERAUSDC",
      "ETCUSDC",
      "ETHFIUSDC",
      "ETHUSDC",
      "EULUSDC",
      "EURIUSDC",
      "EURUSDC",
      "FETUSDC",
      "FFUSDC",
      "FILUSDC",
      "FLOKIUSDC",
      "FLUXUSDC",
      "FORMUSDC",
      "FUNUSDC",
      "FUSDC",
      "GALAUSDC",
      "GIGGLEUSDC",
      "GMTUSDC",
      "GMXUSDC",
      "GPSUSDC",
      "GRTUSDC",
      "GUNUSDC",
      "HAEDALUSDC",
      "HBARUSDC",
      "HEIUSDC",
      "HEMIUSDC",
      "HIVEUSDC",
      "HOLOUSDC",
      "HOMEUSDC",
      "HUMAUSDC",
      "HYPERUSDC",
      "ICPUSDC",
      "IDEXUSDC",
      "ILVUSDC",
      "IMXUSDC",
      "INITUSDC",
      "INJUSDC",
      "IOTAUSDC",
      "IOUSDC",
      "JTOUSDC",
      "JUPUSDC",
      "JUVUSDC",
      "KAIAUSDC",
      "KAITOUSDC",
      "KERNELUSDC",
      "KITEUSDC",
      "KMNOUSDC",
      "LAUSDC",
      "LAYERUSDC",
      "LDOUSDC",
      "LINEAUSDC",
      "LINKUSDC",
      "LISTAUSDC",
      "LPTUSDC",
      "LSKUSDC",
      "LTCUSDC",
      "LUNAUSDC",
      "LUNCUSDC",
      "MAGICUSDC",
      "MANTAUSDC",
      "MASKUSDC",
      "MAVUSDC",
      "MEMEUSDC",
      "METUSDC",
      "MEUSDC",
      "MINAUSDC",
      "MIRAUSDC",
      "MITOUSDC",
      "MMTUSDC",
      "MORPHOUSDC",
      "MOVEUSDC",
      "MUBARAKUSDC",
      "NEARUSDC",
      "NEIROUSDC",
      "NEOUSDC",
      "NEWTUSDC",
      "NILUSDC",
      "NMRUSDC",
      "NOMUSDC",
      "NOTUSDC",
      "NXPCUSDC",
      "OMUSDC",
      "ONDOUSDC",
      "ONTUSDC",
      "OPENUSDC",
      "OPUSDC",
      "ORCAUSDC",
      "ORDIUSDC",
      "OSMOUSDC",
      "PARTIUSDC",
      "PENDLEUSDC",
      "PENGUUSDC",
      "PEOPLEUSDC",
      "PEPEUSDC",
      "PHAUSDC",
      "PIXELUSDC",
      "PLUMEUSDC",
      "PNUTUSDC",
      "POLUSDC",
      "PROVEUSDC",
      "PUMPUSDC",
      "PUNDIXUSDC",
      "PYTHUSDC",
      "QNTUSDC",
      "QTUMUSDC",
      "RAREUSDC",
      "RAYUSDC",
      "REDUSDC",
      "RENDERUSDC",
      "RESOLVUSDC",
      "REZUSDC",
      "ROSEUSDC",
      "RPLUSDC",
      "RSRUSDC",
      "RUNEUSDC",
      "RVNUSDC",
      "SAGAUSDC",
      "SAHARAUSDC",
      "SANDUSDC",
      "SAPIENUSDC",
      "SEIUSDC",
      "SHELLUSDC",
      "SIGNUSDC",
      "SKLUSDC",
      "SKYUSDC",
      "SNXUSDC",
      "SOLUSDC",
      "SOLVUSDC",
      "SOMIUSDC",
      "SOPHUSDC",
      "SPKUSDC",
      "SSVUSDC",
      "STEEMUSDC",
      "STOUSDC",
      "STRKUSDC",
      "STXUSDC",
      "SUIUSDC",
      "SUSDC",
      "SUSHIUSDC",
      "SXTUSDC",
      "SYNUSDC",
      "SYRUPUSDC",
      "TAOUSDC",
      "THETAUSDC",
      "THEUSDC",
      "TIAUSDC",
      "TLMUSDC",
      "TNSRUSDC",
      "TONUSDC",
      "TOWNSUSDC",
      "TREEUSDC",
      "TRUMPUSDC",
      "TRXUSDC",
      "TSTUSDC",
      "TURBOUSDC",
      "TURTLEUSDC",
      "TUSDC",
      "TUTUSDC",
      "TWTUSDC",
      "UMAUSDC",
      "UNIUSDC",
      "USUALUSDC",
      "UTKUSDC",
      "VANAUSDC",
      "VANRYUSDC",
      "VELODROMEUSDC",
      "VETUSDC",
      "VIRTUALUSDC",
      "WALUSDC",
      "WCTUSDC",
      "WIFUSDC",
      "WLDUSDC",
      "WLFIUSDC",
      "WUSDC",
      "XAIUSDC",
      "XLMUSDC",
      "XPLUSDC",
      "XRPUSDC",
      "XTZUSDC",
      "XVGUSDC",
      "YGGUSDC",
      "ZBTUSDC",
      "ZECUSDC",
      "ZENUSDC",
      "ZKCUSDC",
      "ZKUSDC",
      "ZROUSDC"
    ],
    "XRP": [
      "TRXXRP"
    ],
    "TRX": [
      "WINTRX"
    ],
    "EUR": [
      "ADAEUR",
      "APTEUR",
      "ARBEUR",
      "ATOMEUR",
      "AVAXEUR",
      "BCHEUR",
      "BNBEUR",
      "BTCEUR",
      "DOGEEUR",
      "DOTEUR",
      "EGLDEUR",
      "ETHEUR",
      "GALAEUR",
      "GMTEUR",
      "GRTEUR",
      "ICPEUR",
      "LINKEUR",
      "LTCEUR",
      "NEAREUR",
      "OPEUR",
      "PEPEEUR",
      "PNUTEUR",
      "POLEUR",
      "RENDEREUR",
      "SEUR",
      "SHIBEUR",
      "SOLEUR",
      "SUIEUR",
      "TRUMPEUR",
      "TRXEUR",
      "VETEUR",
      "WIFEUR",
      "WINEUR",
      "WLDEUR",
      "WLFIEUR",
      "XLMEUR",
      "XRPEUR"
    ],
    "ZAR": [
      "BTCZAR",
      "ETHZAR"
    ],
    "UAH": [
      "BTCUAH"
    ],
    "BRL": [
      "ADABRL",
      "AVAXBRL",
      "BNBBRL",
      "BONKBRL",
      "BTCBRL",
      "DOGEBRL",
      "DOTBRL",
      "ENABRL",
      "ETHBRL",
      "GALABRL",
      "LINKBRL",
      "LTCBRL",
      "NEARBRL",
      "PEPEBRL",
      "POLBRL",
      "RENDERBRL",
      "SHIBBRL",
      "SOLBRL",
      "SUIBRL",
      "TRUMPBRL",
      "USDCBRL",
      "XRPBRL"
    ],
    "DOGE": [
      "SHIBDOGE"
    ],
    "PLN": [
      "BTCPLN",
      "ETHPLN",
      "USDCPLN"
    ],
    "ARS": [
      "BNBARS",
      "BTCARS",
      "ETHARS",
      "SOLARS"
    ],
    "JPY": [
      "ADAJPY",
      "APTJPY",
      "BCHJPY",
      "BNBJPY",
      "BTCJPY",
      "DOGEJPY",
      "ETHJPY",
      "IOTXJPY",
      "LINKJPY",
      "LPTJPY",
      "LTCJPY",
      "NEARJPY",
      "NEIROJPY",
      "PEPEJPY",
      "POLJPY",
      "SEIJPY",
      "SHIBJPY",
      "SOLJPY",
      "SUIJPY",
      "TRUMPJPY",
      "TRXJPY",
      "XLMJPY",
      "XRPJPY"
    ],
    "MXN": [
      "BTCMXN",
      "ETHMXN",
      "SOLMXN",
      "XRPMXN"
    ],
    "EURI": [
      "BTCEURI",
      "ETHEURI",
      "EUREURI"
    ],
    "SOL": [
      "BNSOLSOL"
    ],
    "RON": [
      "USDCRON"
    ],
    "CZK": [
      "USDCCZK"
    ],
    "USD": [
      "BTCUSD",
      "USDCUSD"
    ]
  },
  "total_pairs": 662,
  "restricted_tokens": [
    "SXPDOWN",
    "EOSUP",
    "XRPDOWN",
    "BTCUP",
    "ETHDOWN",
    "XRPUP",
    "ADAUP",
    "AAPL",
    "BNBDOWN",
    "AMZN",
    "TRXDOWN",
    "ADADOWN",
    "BNBUP",
    "LINKUP",
    "LINKDOWN",
    "MSFT",
    "BUSD",
    "UNIUP",
    "1INCHUP",
    "COIN",
    "EOSDOWN",
    "DOTDOWN",
    "FILUP",
    "MSTR",
    "1INCHDOWN",
    "SUSHIDOWN",
    "SXPUP",
    "AAVEDOWN",
    "SUSHIUP",
    "DOTUP",
    "ETHUP",
    "AAVEUP",
    "BTCDOWN",
    "UNIDOWN",
    "FILDOWN",
    "TRXUP",
    "GOOGL",
    "TSLA"
  ]
}